create_fake_model_object/__init__.py
create_fake_model_object/management/commands/createrandom.py
django_create_fake_model_object-0.2.dist-info/LICENSE
django_create_fake_model_object-0.2.dist-info/METADATA
django_create_fake_model_object-0.2.dist-info/WHEEL
django_create_fake_model_object-0.2.dist-info/top_level.txt
django_create_fake_model_object-0.2.dist-info/RECORD
