Metadata-Version: 2.1
Name: django-create-fake-model-object
Version: 0.2
Summary: Create Fake Model Object
Home-page: https://github.com/cwadven/django-create-fake-model-object
Author: cwadven
Author-email: cwadven4@gmail.com
Maintainer: cwadven
License: MIT
Keywords: django random
Platform: UNKNOWN
Classifier: Environment :: Web Environment
Classifier: Framework :: Django
Classifier: Intended Audience :: Developers
Classifier: License :: OSI Approved :: MIT License
Classifier: Operating System :: OS Independent
Classifier: Programming Language :: Python :: 3
Classifier: Programming Language :: Python :: 3.6
Classifier: Programming Language :: Python :: 3.7
Classifier: Programming Language :: Python :: 3.8
Classifier: Topic :: Software Development :: Libraries :: Python Modules
Requires-Dist: Faker
Requires-Dist: django-seed
Requires-Dist: psycopg2
Requires-Dist: psycopg2-binary
